{
    "subject": "ELA",
    "grade_level": 5,
    "taxonomy": {
        "College_and_Career_Readiness_Anchor_Standards_for_Reading": {
            "grade_level": 5,
            "type": "core",
            "subtopics": {
                "Key_Ideas_and_Details": {
                    "grade_level": 5,
                    "type": "core",
                    "concepts": [
                        {
                            "label": "CCRA.R.1",
                            "grade_level": 5,
                            "type": "core",
                            "description": "Read closely to determine what the text says explicitly and to make logical inferences from it; cite specific textual evidence when writing or speaking to support conclusions drawn from the text.",
                            "node_type": "core"
                        },
                        {
                            "label": "CCRA.R.2",
                            "grade_level": 5,
                            "type": "core",
                            "description": "Determine central ideas or themes of a text and analyze their development; summarize the key supporting details and ideas.",
                            "node_type": "core"
                        },
                        {
                            "label": "CCRA.R.3",
                            "grade_level": 5,
                            "type": "core",
                            "description": "Analyze how and why individuals, events, and ideas develop and interact over the course of a text.",
                            "node_type": "core"
                        }
                    ]
                },
                "Craft_and_Structure": {
                    "grade_level": 5,
                    "type": "core",
                    "concepts": [
                        {
                            "label": "CCRA.R.4",
                            "grade_level": 5,
                            "type": "core",
                            "description": "Interpret words and phrases as they are used in a text, including determining technical, connotative, and figurative meanings, and analyze how specific word choices shape meaning or tone.",
                            "node_type": "core"
                        },
                        {
                            "label": "CCRA.R.5",
                            "grade_level": 5,
                            "type": "core",
                            "description": "Analyze the structure of texts, including how specific sentences, paragraphs, and larger portions of the text (e.g., a section, chapter, scene, or stanza) relate to each other and the whole.",
                            "node_type": "core"
                        },
                        {
                            "label": "CCRA.R.6",
                            "grade_level": 5,
                            "type": "core",
                            "description": "Assess how point of view or purpose shapes the content and style of a text.",
                            "node_type": "core"
                        }
                    ]
                },
                "Integration_of_Knowledge_and_Ideas": {
                    "grade_level": 5,
                    "type": "core",
                    "concepts": [
                        {
                            "label": "CCRA.R.7",
                            "grade_level": 5,
                            "type": "core",
                            "description": "Integrate and evaluate content presented in diverse media and formats, including visually and quantitatively, as well as in words.",
                            "node_type": "core"
                        },
                        {
                            "label": "CCRA.R.8",
                            "grade_level": 5,
                            "type": "core",
                            "description": "Delineate and evaluate the argument and specific claims in a text, including the validity of the reasoning as well as the relevance and sufficiency of the evidence.",
                            "node_type": "core"
                        },
                        {
                            "label": "CCRA.R.9",
                            "grade_level": 5,
                            "type": "core",
                            "description": "Analyze how two or more texts address similar themes or topics in order to build knowledge or to compare the approaches the authors take.",
                            "node_type": "core"
                        }
                    ]
                },
                "Range_of_Reading_and_Level_of_Text_Complexity": {
                    "grade_level": 5,
                    "type": "core",
                    "concepts": [
                        {
                            "label": "CCRA.R.10",
                            "grade_level": 5,
                            "type": "core",
                            "description": "10. Read and comprehend complex literary and informational texts independently and proficiently.",
                            "node_type": "core"
                        }
                    ]
                }
            }
        },
        "Reading_Standards_for_Literature": {
            "grade_level": 5,
            "type": "core",
            "subtopics": {
                "Key_Ideas_and_Details": {
                    "grade_level": 5,
                    "type": "core",
                    "concepts": [
                        {
                            "label": "RL.5.1",
                            "grade_level": 5,
                            "type": "core",
                            "description": "Quote accurately from a text when explaining what the text says explicitly and when drawing inferences from the text.",
                            "node_type": "core"
                        },
                        {
                            "label": "RL.5.2",
                            "grade_level": 5,
                            "type": "core",
                            "description": "Determine a theme of a story, drama, or poem from details in the text, including how characters in a story or drama respond to challenges or how the speaker in a poem reflects upon a topic; summarize the text.",
                            "node_type": "core"
                        },
                        {
                            "label": "RL.5.3",
                            "grade_level": 5,
                            "type": "core",
                            "description": "Compare and contrast two or more characters, settings, or events in a story or drama, drawing on specific details in the text (e.g., how characters interact).",
                            "node_type": "core"
                        }
                    ]
                },
                "Craft_and_Structure": {
                    "grade_level": 5,
                    "type": "core",
                    "concepts": [
                        {
                            "label": "RL.5.4",
                            "grade_level": 5,
                            "type": "core",
                            "description": "Determine the meaning of words and phrases as they are used in a text, including figurative language such as metaphors and similes.",
                            "node_type": "core"
                        },
                        {
                            "label": "RL.5.5",
                            "grade_level": 5,
                            "type": "core",
                            "description": "Explain how a series of chapters, scenes, or stanzas fits together to provide the overall structure of a particular story, drama, or poem.",
                            "node_type": "core"
                        },
                        {
                            "label": "RL.5.6",
                            "grade_level": 5,
                            "type": "core",
                            "description": "Describe how a narrator's or speaker's point of view influences how events are described.",
                            "node_type": "core"
                        }
                    ]
                },
                "Integration_of_Knowledge_and_Ideas": {
                    "grade_level": 5,
                    "type": "core",
                    "concepts": [
                        {
                            "label": "RL.5.7",
                            "grade_level": 5,
                            "type": "core",
                            "description": "Analyze how visual and multimedia elements contribute to the meaning, tone, or beauty of a text (e.g., graphic novel, multimedia presentation of fiction, folktale, myth, poem).",
                            "node_type": "core"
                        },
                        {
                            "label": "(Not applicable to literature)",
                            "grade_level": 5,
                            "type": "core",
                            "description": "(Not applicable to literature)",
                            "node_type": "core"
                        },
                        {
                            "label": "RL.5.9",
                            "grade_level": 5,
                            "type": "core",
                            "description": "Compare and contrast stories in the same genre (e.g., mysteries and adventure stories) on their approaches to similar themes and topics.",
                            "node_type": "core"
                        }
                    ]
                },
                "Range_of_Reading_and_Level_of_Text_Complexity": {
                    "grade_level": 5,
                    "type": "core",
                    "concepts": [
                        {
                            "label": "RL.5.10",
                            "grade_level": 5,
                            "type": "core",
                            "description": "10. By the end of the year, read and comprehend literature, including stories, dramas, and poetry, at the high end of the grades 4\u20145 text complexity band independently and proficiently.",
                            "node_type": "core"
                        }
                    ]
                }
            }
        },
        "Reading_Standards_for_Informational_Text": {
            "grade_level": 5,
            "type": "core",
            "subtopics": {
                "Key_Ideas_and_Details": {
                    "grade_level": 5,
                    "type": "core",
                    "concepts": [
                        {
                            "label": "RI.5.1",
                            "grade_level": 5,
                            "type": "core",
                            "description": "Quote accurately from a text when explaining what the text says explicitly and when drawing inferences from the text.",
                            "node_type": "core"
                        },
                        {
                            "label": "RI.5.2",
                            "grade_level": 5,
                            "type": "core",
                            "description": "Determine two or more main ideas of a text and explain how they are supported by key details; summarize the text.",
                            "node_type": "core"
                        },
                        {
                            "label": "RI.5.3",
                            "grade_level": 5,
                            "type": "core",
                            "description": "Explain the relationships or interactions between two or more individuals, events, ideas, or concepts in a historical, scientific, or technical text based on specific information in the text.",
                            "node_type": "core"
                        }
                    ]
                },
                "Craft_and_Structure": {
                    "grade_level": 5,
                    "type": "core",
                    "concepts": [
                        {
                            "label": "RI.5.4",
                            "grade_level": 5,
                            "type": "core",
                            "description": "Determine the meaning of general academic and domain-specific words and phrases in a text relevant to a grade 5 topic or subject area.",
                            "node_type": "core"
                        },
                        {
                            "label": "RI.5.5",
                            "grade_level": 5,
                            "type": "core",
                            "description": "Compare and contrast the overall structure (e.g., chronology, comparison, cause/effect, problem/solution) of events, ideas, concepts, or information in two or more texts.",
                            "node_type": "core"
                        },
                        {
                            "label": "RI.5.6",
                            "grade_level": 5,
                            "type": "core",
                            "description": "Analyze multiple accounts of the same event or topic, noting important similarities and differences in the point of view they represent.",
                            "node_type": "core"
                        }
                    ]
                },
                "Integration_of_Knowledge_and_Ideas": {
                    "grade_level": 5,
                    "type": "core",
                    "concepts": [
                        {
                            "label": "RI.5.7",
                            "grade_level": 5,
                            "type": "core",
                            "description": "Draw on information from multiple print or digital sources, demonstrating the ability to locate an answer to a question quickly or to solve a problem efficiently.",
                            "node_type": "core"
                        },
                        {
                            "label": "RI.5.8",
                            "grade_level": 5,
                            "type": "core",
                            "description": "Explain how an author uses reasons and evidence to support particular points in a text, identifying which reasons and evidence support which point(s).",
                            "node_type": "core"
                        },
                        {
                            "label": "RI.5.9",
                            "grade_level": 5,
                            "type": "core",
                            "description": "Integrate information from several texts on the same topic in order to write or speak about the subject knowledgeably.",
                            "node_type": "core"
                        }
                    ]
                },
                "Range_of_Reading_and_Level_of_Text_Complexity": {
                    "grade_level": 5,
                    "type": "core",
                    "concepts": [
                        {
                            "label": "RI.5.10",
                            "grade_level": 5,
                            "type": "core",
                            "description": "10. By the end of the year, read and comprehend informational texts, including history/social studies, science, and technical texts, at the high end of the grades 4\u20145 text complexity band independently and proficiently.",
                            "node_type": "core"
                        }
                    ]
                }
            }
        },
        "Reading_Standards_Foundational_Skills": {
            "grade_level": 5,
            "type": "core",
            "subtopics": {
                "Phonics_and_Word_Recognition": {
                    "grade_level": 5,
                    "type": "core",
                    "subtopics": {
                        "RF53": {
                            "grade_level": 5,
                            "type": "core",
                            "concepts": [
                                {
                                    "label": "RF.5.3a",
                                    "grade_level": 5,
                                    "type": "core",
                                    "description": "Use combined knowledge of all letter-sound correspondences, syllabication patterns, and morphology (e.g., roots and affixes) to read accurately unfamiliar multisyllabic words in context and out of context.",
                                    "node_type": "core"
                                }
                            ]
                        }
                    }
                },
                "Fluency": {
                    "grade_level": 5,
                    "type": "core",
                    "subtopics": {
                        "Read_with_sufficient_accuracy_and_fluency_to_support_comprehension": {
                            "grade_level": 5,
                            "type": "core",
                            "concepts": [
                                {
                                    "label": "RF.1-5.4a",
                                    "grade_level": 5,
                                    "type": "core",
                                    "description": "Read on-level text with purpose and understanding.",
                                    "node_type": "core"
                                },
                                {
                                    "label": "RF.3-5.4b",
                                    "grade_level": 5,
                                    "type": "core",
                                    "description": "Read on-level prose and poetry orally with accuracy, appropriate rate, and expression on successive readings",
                                    "node_type": "core"
                                },
                                {
                                    "label": "RF.3-5.4c",
                                    "grade_level": 5,
                                    "type": "core",
                                    "description": "Use context to confirm or self-correct word recognition and understanding, rereading as necessary.",
                                    "node_type": "core"
                                }
                            ]
                        }
                    }
                }
            }
        },
        "College_and_Career_Readiness_Anchor_Standards_for_Writing": {
            "grade_level": 5,
            "type": "core",
            "subtopics": {
                "Text_Types_and_Purposes": {
                    "grade_level": 5,
                    "type": "core",
                    "concepts": [
                        {
                            "label": "CCRA.W.1",
                            "grade_level": 5,
                            "type": "core",
                            "description": "Write arguments to support claims in an analysis of substantive topics or texts, using valid reasoning and relevant and sufficient evidence.",
                            "node_type": "core"
                        },
                        {
                            "label": "CCRA.W.2",
                            "grade_level": 5,
                            "type": "core",
                            "description": "Write informative/explanatory texts to examine and convey complex ideas and information clearly and accurately through the effective selection, organization, and analysis of content.",
                            "node_type": "core"
                        },
                        {
                            "label": "CCRA.W.3",
                            "grade_level": 5,
                            "type": "core",
                            "description": "Write narratives to develop real or imagined experiences or events using effective technique, well-chosen details, and well-structured event sequences.",
                            "node_type": "core"
                        }
                    ]
                },
                "Production_and_Distribution_of_Writing": {
                    "grade_level": 5,
                    "type": "core",
                    "concepts": [
                        {
                            "label": "CCRA.W.4",
                            "grade_level": 5,
                            "type": "core",
                            "description": "Produce clear and coherent writing in which the development, organization, and style are appropriate to task, purpose, and audience.",
                            "node_type": "core"
                        },
                        {
                            "label": "CCRA.W.5",
                            "grade_level": 5,
                            "type": "core",
                            "description": "Develop and strengthen writing as needed by planning, revising, editing, rewriting, or trying a new approach.",
                            "node_type": "core"
                        },
                        {
                            "label": "CCRA.W.6",
                            "grade_level": 5,
                            "type": "core",
                            "description": "Use technology, including the Internet, to produce and publish writing and to interact and collaborate with others.",
                            "node_type": "core"
                        }
                    ]
                },
                "Research_to_Build_and_Present_Knowledge": {
                    "grade_level": 5,
                    "type": "core",
                    "concepts": [
                        {
                            "label": "CCRA.W.7",
                            "grade_level": 5,
                            "type": "core",
                            "description": "Conduct short as well as more sustained research projects based on focused questions, demonstrating understanding of the subject under investigation.",
                            "node_type": "core"
                        },
                        {
                            "label": "CCRA.W.8",
                            "grade_level": 5,
                            "type": "core",
                            "description": "Gather relevant information from multiple print and digital sources, assess the credibility and accuracy of each source, and integrate the information while avoiding plagiarism.",
                            "node_type": "core"
                        },
                        {
                            "label": "CCRA.W.9",
                            "grade_level": 5,
                            "type": "core",
                            "description": "Draw evidence from literary or informational texts to support analysis, reflection, and research.",
                            "node_type": "core"
                        }
                    ]
                },
                "Range_of_Writing": {
                    "grade_level": 5,
                    "type": "core",
                    "concepts": [
                        {
                            "label": "CCRA.W.10",
                            "grade_level": 5,
                            "type": "core",
                            "description": "10. Write routinely over extended time frames (time for research, reflection, and revision) and shorter time frames (a single sitting or a day or two) for a range of tasks, purposes, and audiences.",
                            "node_type": "core"
                        }
                    ]
                }
            }
        },
        "Writing_Standards": {
            "grade_level": 5,
            "type": "core",
            "subtopics": {
                "Text_Types_and_Purposes": {
                    "grade_level": 5,
                    "type": "core",
                    "subtopics": {
                        "W51": {
                            "grade_level": 5,
                            "type": "core",
                            "concepts": [
                                {
                                    "label": "W.5.1a",
                                    "grade_level": 5,
                                    "type": "core",
                                    "description": "Introduce a topic or text clearly, state an opinion, and create an organizational structure in which ideas are logically grouped to support the writer's purpose.",
                                    "node_type": "core"
                                },
                                {
                                    "label": "W.5.1b",
                                    "grade_level": 5,
                                    "type": "core",
                                    "description": "Provide logically ordered reasons that are supported by facts and details.",
                                    "node_type": "core"
                                },
                                {
                                    "label": "W.5.1c",
                                    "grade_level": 5,
                                    "type": "core",
                                    "description": "Link opinion and reasons using words, phrases, and clauses (e.g., consequently, specifically).",
                                    "node_type": "core"
                                },
                                {
                                    "label": "W.5.1d",
                                    "grade_level": 5,
                                    "type": "core",
                                    "description": "Provide a concluding statement or section related to the opinion presented.",
                                    "node_type": "core"
                                }
                            ]
                        },
                        "W52": {
                            "grade_level": 5,
                            "type": "core",
                            "concepts": [
                                {
                                    "label": "W.5.2a",
                                    "grade_level": 5,
                                    "type": "core",
                                    "description": "Introduce a topic clearly, provide a general observation and focus, and group related information logically; include formatting (e.g., headings), illustrations, and multimedia when useful to aiding comprehension.",
                                    "node_type": "core"
                                },
                                {
                                    "label": "W.5.2b",
                                    "grade_level": 5,
                                    "type": "core",
                                    "description": "Develop the topic with facts, definitions, concrete details, quotations, or other information and examples related to the topic.",
                                    "node_type": "core"
                                },
                                {
                                    "label": "W.5.2c",
                                    "grade_level": 5,
                                    "type": "core",
                                    "description": "Link ideas within and across categories of information using words, phrases, and clauses (e.g., in contrast, especially).",
                                    "node_type": "core"
                                },
                                {
                                    "label": "W.5.2d",
                                    "grade_level": 5,
                                    "type": "core",
                                    "description": "Use precise language and domain-specific vocabulary to inform about or explain the topic.",
                                    "node_type": "core"
                                },
                                {
                                    "label": "W.5.2e",
                                    "grade_level": 5,
                                    "type": "core",
                                    "description": "Provide a concluding statement or section related to the information or explanation presented",
                                    "node_type": "core"
                                }
                            ]
                        },
                        "W53": {
                            "grade_level": 5,
                            "type": "core",
                            "concepts": [
                                {
                                    "label": "W.5.3a",
                                    "grade_level": 5,
                                    "type": "core",
                                    "description": "Orient the reader by establishing a situation and introducing a narrator and/or characters; organize an event sequence that unfolds naturally.",
                                    "node_type": "core"
                                },
                                {
                                    "label": "W.5.3b",
                                    "grade_level": 5,
                                    "type": "core",
                                    "description": "Use narrative techniques, such as dialogue, description, and pacing, to develop experiences and events or show the responses of characters to situations.",
                                    "node_type": "core"
                                },
                                {
                                    "label": "W.5.3c",
                                    "grade_level": 5,
                                    "type": "core",
                                    "description": "Use a variety of transitional words, phrases, and clauses to manage the sequence of events.",
                                    "node_type": "core"
                                },
                                {
                                    "label": "W.5.3d",
                                    "grade_level": 5,
                                    "type": "core",
                                    "description": "Use concrete words and phrases and sensory details to convey experiences and events precisely.",
                                    "node_type": "core"
                                },
                                {
                                    "label": "W.5.3e",
                                    "grade_level": 5,
                                    "type": "core",
                                    "description": "Provide a conclusion that follows from the narrated experiences or events.",
                                    "node_type": "core"
                                }
                            ]
                        }
                    }
                },
                "Production_and_Distribution_of_Writing": {
                    "grade_level": 5,
                    "type": "core",
                    "concepts": [
                        {
                            "label": "W.5.4",
                            "grade_level": 5,
                            "type": "core",
                            "description": "Produce clear and coherent writing in which the development and organization are appropriate to task, purpose, and audience.",
                            "node_type": "core"
                        },
                        {
                            "label": "W.5.5",
                            "grade_level": 5,
                            "type": "core",
                            "description": "With guidance and support from peers and adults, develop and strengthen writing as needed by planning, revising, editing, rewriting, or trying a new approach.",
                            "node_type": "core"
                        },
                        {
                            "label": "W.5.6",
                            "grade_level": 5,
                            "type": "core",
                            "description": "With some guidance and support from adults, use technology, including the Internet, to produce and publish writing as well as to interact and collaborate with others; demonstrate sufficient command of keyboarding skills to type a minimum of two pages in a single sitting.",
                            "node_type": "core"
                        }
                    ]
                },
                "Research_to_Build_and_Present_Knowledge": {
                    "grade_level": 5,
                    "type": "core",
                    "subtopics": {
                        "W59": {
                            "grade_level": 5,
                            "type": "core",
                            "concepts": [
                                {
                                    "label": "W.5.9a",
                                    "grade_level": 5,
                                    "type": "core",
                                    "description": "Apply grade 5 Reading standards to literature (e.g., &quot;Compare and contrast two or more characters, settings, or events in a story or a drama, drawing on specific details in the text [e.g., how characters interact]&quot;).",
                                    "node_type": "core"
                                },
                                {
                                    "label": "W.5.9b",
                                    "grade_level": 5,
                                    "type": "core",
                                    "description": "Apply grade 5 Reading standards to informational texts (e.g., &quot;Explain how an author uses reasons and evidence to support particular points in a text, identifying which reasons and evidence support which point[s]&quot;).",
                                    "node_type": "core"
                                }
                            ]
                        }
                    },
                    "concepts": [
                        {
                            "label": "W.5.7",
                            "grade_level": 5,
                            "type": "core",
                            "description": "Conduct short research projects that use several sources to build knowledge through investigation of different aspects of a topic.",
                            "node_type": "core"
                        },
                        {
                            "label": "W.5.8",
                            "grade_level": 5,
                            "type": "core",
                            "description": "Recall relevant information from experiences or gather relevant information from print and digital sources; summarize or paraphrase information in notes and finished work, and provide a list of sources.",
                            "node_type": "core"
                        }
                    ]
                },
                "Range_of_Writing": {
                    "grade_level": 5,
                    "type": "core",
                    "concepts": [
                        {
                            "label": "W.5.10",
                            "grade_level": 5,
                            "type": "core",
                            "description": "10. Write routinely over extended time frames (time for research, reflection, and revision) and shorter time frames (a single sitting or a day or two) for a range of discipline-specific tasks, purposes, and audiences.",
                            "node_type": "core"
                        }
                    ]
                }
            }
        },
        "College_and_Career_Readiness_Anchor_Standards_for_Speaking_and_Listening": {
            "grade_level": 5,
            "type": "core",
            "subtopics": {
                "Comprehension_and_Collaboration": {
                    "grade_level": 5,
                    "type": "core",
                    "concepts": [
                        {
                            "label": "CCRA.SL.1",
                            "grade_level": 5,
                            "type": "core",
                            "description": "Prepare for and participate effectively in a range of conversations and collaborations with diverse partners, building on others' ideas and expressing their own clearly and persuasively.",
                            "node_type": "core"
                        },
                        {
                            "label": "CCRA.SL.2",
                            "grade_level": 5,
                            "type": "core",
                            "description": "Integrate and evaluate information presented in diverse media and formats, including visually, quantitatively, and orally.",
                            "node_type": "core"
                        },
                        {
                            "label": "CCRA.SL.3",
                            "grade_level": 5,
                            "type": "core",
                            "description": "Evaluate a speaker's point of view, reasoning, and use of evidence and rhetoric.",
                            "node_type": "core"
                        }
                    ]
                },
                "Presentation_of_Knowledge_and_Ideas": {
                    "grade_level": 5,
                    "type": "core",
                    "concepts": [
                        {
                            "label": "CCRA.SL.4",
                            "grade_level": 5,
                            "type": "core",
                            "description": "Present information, findings, and supporting evidence such that listeners can follow the line of reasoning and the organization, development, and style are appropriate to task, purpose, and audience.",
                            "node_type": "core"
                        },
                        {
                            "label": "CCRA.SL.5",
                            "grade_level": 5,
                            "type": "core",
                            "description": "Make strategic use of digital media and visual displays of data to express information and enhance understanding of presentations.",
                            "node_type": "core"
                        },
                        {
                            "label": "CCRA.SL.6",
                            "grade_level": 5,
                            "type": "core",
                            "description": "Adapt speech to a variety of contexts and communicative tasks, demonstrating command of formal English when indicated or appropriate.",
                            "node_type": "core"
                        }
                    ]
                }
            }
        },
        "Speaking_and_Listening_Standards": {
            "grade_level": 5,
            "type": "core",
            "subtopics": {
                "Comprehension_and_Collaboration": {
                    "grade_level": 5,
                    "type": "core",
                    "subtopics": {
                        "SL51": {
                            "grade_level": 5,
                            "type": "core",
                            "concepts": [
                                {
                                    "label": "SL.5.1a",
                                    "grade_level": 5,
                                    "type": "core",
                                    "description": "Come to discussions prepared, having read or studied required material; explicitly draw on that preparation and other information known about the topic to explore ideas under discussion.",
                                    "node_type": "core"
                                },
                                {
                                    "label": "SL.5.1b",
                                    "grade_level": 5,
                                    "type": "core",
                                    "description": "Follow agreed-upon rules for discussions and carry out assigned roles.",
                                    "node_type": "core"
                                },
                                {
                                    "label": "SL.5.1c",
                                    "grade_level": 5,
                                    "type": "core",
                                    "description": "Pose and respond to specific questions by making comments that contribute to the discussion and elaborate on the remarks of others.",
                                    "node_type": "core"
                                },
                                {
                                    "label": "SL.5.1d",
                                    "grade_level": 5,
                                    "type": "core",
                                    "description": "Review the key ideas expressed and draw conclusions in light of information and knowledge gained from the discussions.",
                                    "node_type": "core"
                                }
                            ]
                        }
                    },
                    "concepts": [
                        {
                            "label": "SL.5.2",
                            "grade_level": 5,
                            "type": "core",
                            "description": "Summarize a written text read aloud or information presented in diverse media and formats, including visually, quantitatively, and orally.",
                            "node_type": "core"
                        },
                        {
                            "label": "SL.5.3",
                            "grade_level": 5,
                            "type": "core",
                            "description": "Summarize the points a speaker makes and explain how each claim is supported by reasons and evidence.",
                            "node_type": "core"
                        }
                    ]
                },
                "Presentation_of_Knowledge_and_Ideas": {
                    "grade_level": 5,
                    "type": "core",
                    "concepts": [
                        {
                            "label": "SL.5.4",
                            "grade_level": 5,
                            "type": "core",
                            "description": "Report on a topic or text or present an opinion, sequencing ideas logically and using appropriate facts and relevant, descriptive details to support main ideas or themes; speak clearly at an understandable pace.",
                            "node_type": "core"
                        },
                        {
                            "label": "SL.5.5",
                            "grade_level": 5,
                            "type": "core",
                            "description": "Include multimedia components (e.g., graphics, sound) and visual displays in presentations when appropriate to enhance the development of main ideas or themes.",
                            "node_type": "core"
                        },
                        {
                            "label": "SL.5.6",
                            "grade_level": 5,
                            "type": "core",
                            "description": "Adapt speech to a variety of contexts and tasks, using formal English when appropriate to task and situation.",
                            "node_type": "core"
                        }
                    ]
                }
            }
        },
        "College_and_Career_Readiness_Anchor_Standards_for_Language": {
            "grade_level": 5,
            "type": "core",
            "subtopics": {
                "Conventions_of_Standard_English": {
                    "grade_level": 5,
                    "type": "core",
                    "concepts": [
                        {
                            "label": "CCRA.L.1",
                            "grade_level": 5,
                            "type": "core",
                            "description": "Demonstrate command of the conventions of standard English grammar and usage when writing or speaking.",
                            "node_type": "core"
                        },
                        {
                            "label": "CCRA.L.2",
                            "grade_level": 5,
                            "type": "core",
                            "description": "Demonstrate command of the conventions of standard English capitalization, punctuation, and spelling when writing.",
                            "node_type": "core"
                        }
                    ]
                },
                "Knowledge_of_Language": {
                    "grade_level": 5,
                    "type": "core",
                    "concepts": [
                        {
                            "label": "CCRA.L.3",
                            "grade_level": 5,
                            "type": "core",
                            "description": "Apply knowledge of language to understand how language functions in different contexts, to make effective choices for meaning or style, and to comprehend more fully when reading or listening.",
                            "node_type": "core"
                        }
                    ]
                },
                "Vocabulary_Acquisition_and_Use": {
                    "grade_level": 5,
                    "type": "core",
                    "concepts": [
                        {
                            "label": "CCRA.L.4",
                            "grade_level": 5,
                            "type": "core",
                            "description": "Determine or clarify the meaning of unknown and multiple-meaning words and phrases by using context clues, analyzing meaningful word parts, and consulting general and specialized reference materials, as appropriate.",
                            "node_type": "core"
                        },
                        {
                            "label": "CCRA.L.5",
                            "grade_level": 5,
                            "type": "core",
                            "description": "Demonstrate understanding of figurative language, word relationships, and nuances in word meanings.",
                            "node_type": "core"
                        },
                        {
                            "label": "CCRA.L.6",
                            "grade_level": 5,
                            "type": "core",
                            "description": "Acquire and use accurately a range of general academic and domain-specific words and phrases sufficient for reading, writing, speaking, and listening at the college and career readiness level; demonstrate independence in gathering vocabulary knowledge when encountering an unknown term important to comprehension or expression.",
                            "node_type": "core"
                        }
                    ]
                }
            }
        },
        "Language_Standards": {
            "grade_level": 5,
            "type": "core",
            "subtopics": {
                "Conventions_of_Standard_English": {
                    "grade_level": 5,
                    "type": "core",
                    "subtopics": {
                        "L51": {
                            "grade_level": 5,
                            "type": "core",
                            "concepts": [
                                {
                                    "label": "L.5.1a",
                                    "grade_level": 5,
                                    "type": "core",
                                    "description": "Explain the function of conjunctions, prepositions, and interjections in general and their function in particular sentences.",
                                    "node_type": "core"
                                },
                                {
                                    "label": "L.5.1b",
                                    "grade_level": 5,
                                    "type": "core",
                                    "description": "Form and use the perfect (e.g., I had walked; I have walked; I will have walked) verb tenses.",
                                    "node_type": "core"
                                },
                                {
                                    "label": "L.5.1c",
                                    "grade_level": 5,
                                    "type": "core",
                                    "description": "Use verb tense to convey various times, sequences, states, and conditions.",
                                    "node_type": "core"
                                },
                                {
                                    "label": "L.5.1d",
                                    "grade_level": 5,
                                    "type": "core",
                                    "description": "Recognize and correct inappropriate shifts in verb tense.",
                                    "node_type": "core"
                                },
                                {
                                    "label": "L.5.1e",
                                    "grade_level": 5,
                                    "type": "core",
                                    "description": "Use correlative conjunctions (e.g., either/or, neither/nor).",
                                    "node_type": "core"
                                }
                            ]
                        },
                        "L52": {
                            "grade_level": 5,
                            "type": "core",
                            "concepts": [
                                {
                                    "label": "L.5.2a",
                                    "grade_level": 5,
                                    "type": "core",
                                    "description": "Use punctuation to separate items in a series.",
                                    "node_type": "core"
                                },
                                {
                                    "label": "L.5.2b",
                                    "grade_level": 5,
                                    "type": "core",
                                    "description": "Use a comma to separate an introductory element from the rest of the sentence.",
                                    "node_type": "core"
                                },
                                {
                                    "label": "L.5.2c",
                                    "grade_level": 5,
                                    "type": "core",
                                    "description": "Use a comma to set off the words yes and no (e.g., Yes, thank you), to set off a tag question from the rest of the sentence (e.g., It's true, isn't it?), and to indicate direct address (e.g., Is that you, Steve?).",
                                    "node_type": "core"
                                },
                                {
                                    "label": "L.5.2d",
                                    "grade_level": 5,
                                    "type": "core",
                                    "description": "Use underlining, quotation marks, or italics to indicate titles of works.",
                                    "node_type": "core"
                                },
                                {
                                    "label": "L.5.2e",
                                    "grade_level": 5,
                                    "type": "core",
                                    "description": "Spell grade-appropriate words correctly, consulting references as needed.",
                                    "node_type": "core"
                                }
                            ]
                        }
                    }
                },
                "Knowledge_of_Language": {
                    "grade_level": 5,
                    "type": "core",
                    "subtopics": {
                        "L53": {
                            "grade_level": 5,
                            "type": "core",
                            "concepts": [
                                {
                                    "label": "L.5.3a",
                                    "grade_level": 5,
                                    "type": "core",
                                    "description": "Expand, combine, and reduce sentences for meaning, reader/listener interest, and style.",
                                    "node_type": "core"
                                },
                                {
                                    "label": "L.5.3b",
                                    "grade_level": 5,
                                    "type": "core",
                                    "description": "Compare and contrast the varieties of English (e.g., dialects, registers) used in stories, dramas, or poems.",
                                    "node_type": "core"
                                }
                            ]
                        }
                    }
                },
                "Vocabulary_Acquisition_and_Use": {
                    "grade_level": 5,
                    "type": "core",
                    "subtopics": {
                        "L54": {
                            "grade_level": 5,
                            "type": "core",
                            "concepts": [
                                {
                                    "label": "L.5.4a",
                                    "grade_level": 5,
                                    "type": "core",
                                    "description": "Use context (e.g., cause/effect relationships and comparisons in text) as a clue to the meaning of a word or phrase.",
                                    "node_type": "core"
                                },
                                {
                                    "label": "L.5.4b",
                                    "grade_level": 5,
                                    "type": "core",
                                    "description": "Use common, grade-appropriate Greek and Latin affixes and roots as clues to the meaning of a word (e.g., photograph, photosynthesis).",
                                    "node_type": "core"
                                },
                                {
                                    "label": "L.5.4c",
                                    "grade_level": 5,
                                    "type": "core",
                                    "description": "Consult reference materials (e.g., dictionaries, glossaries, thesauruses), both print and digital, to find the pronunciation and determine or clarify the precise meaning of key words and phrases.",
                                    "node_type": "core"
                                }
                            ]
                        },
                        "L55": {
                            "grade_level": 5,
                            "type": "core",
                            "concepts": [
                                {
                                    "label": "L.5.5a",
                                    "grade_level": 5,
                                    "type": "core",
                                    "description": "Interpret figurative language, including similes and metaphors, in context.",
                                    "node_type": "core"
                                },
                                {
                                    "label": "L.5.5b",
                                    "grade_level": 5,
                                    "type": "core",
                                    "description": "Recognize and explain the meaning of common idioms, adages, and proverbs.",
                                    "node_type": "core"
                                },
                                {
                                    "label": "L.5.5c",
                                    "grade_level": 5,
                                    "type": "core",
                                    "description": "Use the relationship between particular words (e.g., synonyms, antonyms, homographs) to better understand each of the words.",
                                    "node_type": "core"
                                }
                            ]
                        }
                    },
                    "concepts": [
                        {
                            "label": "L.5.6",
                            "grade_level": 5,
                            "type": "core",
                            "description": "Acquire and use accurately grade-appropriate general academic and domain-specific words and phrases, including those that signal contrast, addition, and other logical relationships (e.g., however, although, nevertheless, similarly, moreover, in addition).",
                            "node_type": "core"
                        }
                    ]
                }
            }
        }
    }
}